fmn_messages/__init__.py
fmn_messages/base.py
fmn_messages/rule.py
fmn_messages-1.0.0.dist-info/LICENSES/LGPL-3.0-or-later.txt
fmn_messages-1.0.0.dist-info/LICENSES/MIT.txt
fmn_messages-1.0.0.dist-info/METADATA
fmn_messages-1.0.0.dist-info/WHEEL
fmn_messages-1.0.0.dist-info/entry_points.txt
fmn_messages-1.0.0.dist-info/RECORD
