Metadata-Version: 2.1
Name: fmn-messages
Version: 1.0.0
Summary: A schema package for messages sent by FMN
Home-page: http://github.com/fedora-infra/fmn-messages
License: LGPL-3.0-or-later
Keywords: fedora-messaging
Author: Fedora Infrastructure Team
Author-email: infrastructure@lists.fedoraproject.org
Requires-Python: >=3.8.10,<4.0.0
Classifier: Development Status :: 5 - Production/Stable
Classifier: Intended Audience :: System Administrators
Classifier: License :: OSI Approved :: GNU Lesser General Public License v3 or later (LGPLv3+)
Classifier: Operating System :: POSIX :: Linux
Classifier: Programming Language :: Python :: 3
Classifier: Programming Language :: Python :: 3.9
Classifier: Programming Language :: Python :: 3.10
Classifier: Programming Language :: Python :: 3.11
Classifier: Programming Language :: Python :: 3.12
Classifier: Programming Language :: Python :: 3.8
Classifier: Topic :: Communications
Classifier: Topic :: Software Development :: Libraries :: Python Modules
Requires-Dist: fedora-messaging (>=3.3.0,<4.0.0)
Project-URL: Repository, http://github.com/fedora-infra/fmn-messages
